{
  "id": "3000178",
  "name": "myfonts",
  "font_family": "iconfont",
  "css_prefix_text": "icon-",
  "description": "",
  "glyphs": [
    {
      "icon_id": "144706",
      "name": "密码",
      "font_class": "mima",
      "unicode": "e648",
      "unicode_decimal": 58952
    },
    {
      "icon_id": "435928",
      "name": "密码",
      "font_class": "mima1",
      "unicode": "e7b8",
      "unicode_decimal": 59320
    },
    {
      "icon_id": "813696",
      "name": "密码",
      "font_class": "mima2",
      "unicode": "e649",
      "unicode_decimal": 58953
    },
    {
      "icon_id": "1129591",
      "name": "密码",
      "font_class": "mima3",
      "unicode": "e64b",
      "unicode_decimal": 58955
    },
    {
      "icon_id": "1130615",
      "name": "密码",
      "font_class": "mima4",
      "unicode": "e64c",
      "unicode_decimal": 58956
    },
    {
      "icon_id": "1277254",
      "name": "password",
      "font_class": "password",
      "unicode": "e64e",
      "unicode_decimal": 58958
    },
    {
      "icon_id": "1435237",
      "name": "密码",
      "font_class": "mima5",
      "unicode": "e64f",
      "unicode_decimal": 58959
    },
    {
      "icon_id": "6284047",
      "name": "密码",
      "font_class": "mima6",
      "unicode": "e650",
      "unicode_decimal": 58960
    },
    {
      "icon_id": "6400627",
      "name": "密码（1）",
      "font_class": "weibiaoti--",
      "unicode": "e655",
      "unicode_decimal": 58965
    },
    {
      "icon_id": "6582317",
      "name": "密码",
      "font_class": "mima7",
      "unicode": "e657",
      "unicode_decimal": 58967
    },
    {
      "icon_id": "11372676",
      "name": "密码",
      "font_class": "mima8",
      "unicode": "e8b2",
      "unicode_decimal": 59570
    },
    {
      "icon_id": "11518450",
      "name": "密码",
      "font_class": "mima9",
      "unicode": "e65e",
      "unicode_decimal": 58974
    },
    {
      "icon_id": "19662661",
      "name": "密码",
      "font_class": "mima10",
      "unicode": "e65f",
      "unicode_decimal": 58975
    },
    {
      "icon_id": "49685",
      "name": "文章",
      "font_class": "24",
      "unicode": "e631",
      "unicode_decimal": 58929
    },
    {
      "icon_id": "433395",
      "name": "个人中心",
      "font_class": "gerenzhongxin",
      "unicode": "e68b",
      "unicode_decimal": 59019
    },
    {
      "icon_id": "741952",
      "name": "退出",
      "font_class": "tuichu",
      "unicode": "e652",
      "unicode_decimal": 58962
    },
    {
      "icon_id": "745284",
      "name": "个人中心",
      "font_class": "icon03",
      "unicode": "e632",
      "unicode_decimal": 58930
    },
    {
      "icon_id": "827977",
      "name": "文章1",
      "font_class": "wenzhang1",
      "unicode": "e6a9",
      "unicode_decimal": 59049
    },
    {
      "icon_id": "830347",
      "name": "个人中心",
      "font_class": "icon7",
      "unicode": "e663",
      "unicode_decimal": 58979
    },
    {
      "icon_id": "924719",
      "name": "文章",
      "font_class": "wenzhang",
      "unicode": "e633",
      "unicode_decimal": 58931
    },
    {
      "icon_id": "963809",
      "name": "个人中心",
      "font_class": "gerenzhongxin1",
      "unicode": "e636",
      "unicode_decimal": 58934
    },
    {
      "icon_id": "1279424",
      "name": "个人中心",
      "font_class": "gerenzhongxin2",
      "unicode": "e65d",
      "unicode_decimal": 58973
    },
    {
      "icon_id": "1343817",
      "name": "个人中心",
      "font_class": "gerenzhongxin3",
      "unicode": "e637",
      "unicode_decimal": 58935
    },
    {
      "icon_id": "1440640",
      "name": "个人中心",
      "font_class": "gerenzhongxin4",
      "unicode": "e651",
      "unicode_decimal": 58961
    },
    {
      "icon_id": "2325938",
      "name": "退出",
      "font_class": "tuichu1",
      "unicode": "e643",
      "unicode_decimal": 58947
    },
    {
      "icon_id": "2471395",
      "name": "文章",
      "font_class": "wenzhang2",
      "unicode": "e67e",
      "unicode_decimal": 59006
    },
    {
      "icon_id": "4268507",
      "name": "个人中心",
      "font_class": "gerenzhongxin5",
      "unicode": "e63e",
      "unicode_decimal": 58942
    },
    {
      "icon_id": "4784089",
      "name": "个人中心",
      "font_class": "gerenzhongxin6",
      "unicode": "e653",
      "unicode_decimal": 58963
    },
    {
      "icon_id": "4867099",
      "name": "退出",
      "font_class": "tuichu2",
      "unicode": "e658",
      "unicode_decimal": 58968
    },
    {
      "icon_id": "7093672",
      "name": "个人中心",
      "font_class": "gerenzhongxin7",
      "unicode": "e71d",
      "unicode_decimal": 59165
    },
    {
      "icon_id": "9148454",
      "name": "主页",
      "font_class": "zhuye",
      "unicode": "e63f",
      "unicode_decimal": 58943
    },
    {
      "icon_id": "9795863",
      "name": "退出",
      "font_class": "tuichu3",
      "unicode": "e642",
      "unicode_decimal": 58946
    },
    {
      "icon_id": "10199164",
      "name": "退出",
      "font_class": "tuichu4",
      "unicode": "e645",
      "unicode_decimal": 58949
    },
    {
      "icon_id": "11124968",
      "name": "文章",
      "font_class": "16",
      "unicode": "e646",
      "unicode_decimal": 58950
    },
    {
      "icon_id": "12435114",
      "name": "个人中心",
      "font_class": "gerenzhongxin8",
      "unicode": "e72a",
      "unicode_decimal": 59178
    },
    {
      "icon_id": "12889877",
      "name": "个人中心",
      "font_class": "gerenzhongxin9",
      "unicode": "e647",
      "unicode_decimal": 58951
    },
    {
      "icon_id": "1269",
      "name": "加",
      "font_class": "jia",
      "unicode": "e605",
      "unicode_decimal": 58885
    },
    {
      "icon_id": "1302",
      "name": "加",
      "font_class": "jia1",
      "unicode": "e608",
      "unicode_decimal": 58888
    },
    {
      "icon_id": "521075",
      "name": "关闭",
      "font_class": "guanbi",
      "unicode": "e62e",
      "unicode_decimal": 58926
    },
    {
      "icon_id": "577312",
      "name": "加号",
      "font_class": "jiahao",
      "unicode": "e726",
      "unicode_decimal": 59174
    },
    {
      "icon_id": "577314",
      "name": "加号2-fill",
      "font_class": "jiahao2fill",
      "unicode": "e728",
      "unicode_decimal": 59176
    },
    {
      "icon_id": "651241",
      "name": "加号",
      "font_class": "jiahao1",
      "unicode": "e668",
      "unicode_decimal": 58984
    },
    {
      "icon_id": "677580",
      "name": "加号",
      "font_class": "jiahao2",
      "unicode": "e620",
      "unicode_decimal": 58912
    },
    {
      "icon_id": "712409",
      "name": "关闭",
      "font_class": "icon-cross-squre",
      "unicode": "e66a",
      "unicode_decimal": 58986
    },
    {
      "icon_id": "788018",
      "name": "加号",
      "font_class": "jiahao3",
      "unicode": "e641",
      "unicode_decimal": 58945
    },
    {
      "icon_id": "998485",
      "name": "关闭",
      "font_class": "ai68",
      "unicode": "e6ba",
      "unicode_decimal": 59066
    },
    {
      "icon_id": "1038647",
      "name": "关闭",
      "font_class": "guanbi1",
      "unicode": "e634",
      "unicode_decimal": 58932
    },
    {
      "icon_id": "1166550",
      "name": "加号",
      "font_class": "jiahao4",
      "unicode": "e635",
      "unicode_decimal": 58933
    },
    {
      "icon_id": "1183045",
      "name": "关闭",
      "font_class": "guanbi2",
      "unicode": "e66d",
      "unicode_decimal": 58989
    },
    {
      "icon_id": "1222721",
      "name": "关闭",
      "font_class": "close",
      "unicode": "e644",
      "unicode_decimal": 58948
    },
    {
      "icon_id": "1265484",
      "name": "加号",
      "font_class": "jiahao5",
      "unicode": "e60b",
      "unicode_decimal": 58891
    },
    {
      "icon_id": "1526312",
      "name": "加号",
      "font_class": "jiahao6",
      "unicode": "e660",
      "unicode_decimal": 58976
    },
    {
      "icon_id": "2380639",
      "name": "关闭",
      "font_class": "guanbi3",
      "unicode": "e60e",
      "unicode_decimal": 58894
    },
    {
      "icon_id": "2733956",
      "name": "关闭",
      "font_class": "guanbi4",
      "unicode": "e6e9",
      "unicode_decimal": 59113
    },
    {
      "icon_id": "2939198",
      "name": "加减组件 加号",
      "font_class": "jiajianzujianjiahao",
      "unicode": "e64d",
      "unicode_decimal": 58957
    },
    {
      "icon_id": "4551252",
      "name": "加号",
      "font_class": "jiahao7",
      "unicode": "e617",
      "unicode_decimal": 58903
    },
    {
      "icon_id": "5387527",
      "name": "加号",
      "font_class": "jiahao8",
      "unicode": "eaf3",
      "unicode_decimal": 60147
    },
    {
      "icon_id": "5387866",
      "name": "加号_o",
      "font_class": "jiahao_o",
      "unicode": "eb78",
      "unicode_decimal": 60280
    },
    {
      "icon_id": "5672453",
      "name": "加号",
      "font_class": "jiahao9",
      "unicode": "e729",
      "unicode_decimal": 59177
    },
    {
      "icon_id": "5712912",
      "name": "关闭",
      "font_class": "guanbi5",
      "unicode": "e618",
      "unicode_decimal": 58904
    },
    {
      "icon_id": "6260288",
      "name": "关闭",
      "font_class": "guanbi6",
      "unicode": "e60c",
      "unicode_decimal": 58892
    },
    {
      "icon_id": "6536707",
      "name": "加号",
      "font_class": "jiahao10",
      "unicode": "e656",
      "unicode_decimal": 58966
    },
    {
      "icon_id": "6756281",
      "name": "加号",
      "font_class": "jiahao11",
      "unicode": "e60f",
      "unicode_decimal": 58895
    },
    {
      "icon_id": "7192356",
      "name": "加号",
      "font_class": "jiahao12",
      "unicode": "e721",
      "unicode_decimal": 59169
    },
    {
      "icon_id": "7197182",
      "name": "加号 -16",
      "font_class": "jiahao13",
      "unicode": "e65c",
      "unicode_decimal": 58972
    },
    {
      "icon_id": "7312648",
      "name": "加号",
      "font_class": "jiahao-",
      "unicode": "e610",
      "unicode_decimal": 58896
    },
    {
      "icon_id": "7312822",
      "name": "关闭",
      "font_class": "guanbi-",
      "unicode": "e611",
      "unicode_decimal": 58897
    },
    {
      "icon_id": "7408313",
      "name": "加号",
      "font_class": "jiahao14",
      "unicode": "e63d",
      "unicode_decimal": 58941
    },
    {
      "icon_id": "7515698",
      "name": "关闭",
      "font_class": "guanbi7",
      "unicode": "e619",
      "unicode_decimal": 58905
    },
    {
      "icon_id": "7556876",
      "name": "关闭",
      "font_class": "guanbi8",
      "unicode": "e61a",
      "unicode_decimal": 58906
    },
    {
      "icon_id": "7727117",
      "name": "1加号",
      "font_class": "jiahao15",
      "unicode": "e63c",
      "unicode_decimal": 58940
    },
    {
      "icon_id": "8084557",
      "name": "关闭",
      "font_class": "guanbi9",
      "unicode": "e621",
      "unicode_decimal": 58913
    },
    {
      "icon_id": "8288849",
      "name": "加号",
      "font_class": "jiahao16",
      "unicode": "e84f",
      "unicode_decimal": 59471
    },
    {
      "icon_id": "8288999",
      "name": "加号",
      "font_class": "jiahao17",
      "unicode": "e86a",
      "unicode_decimal": 59498
    },
    {
      "icon_id": "8721197",
      "name": "加号",
      "font_class": "jiahao18",
      "unicode": "e623",
      "unicode_decimal": 58915
    },
    {
      "icon_id": "9626918",
      "name": "加号",
      "font_class": "jiahao19",
      "unicode": "e879",
      "unicode_decimal": 59513
    },
    {
      "icon_id": "9713058",
      "name": "关闭",
      "font_class": "guanbi10",
      "unicode": "e67d",
      "unicode_decimal": 59005
    },
    {
      "icon_id": "10496865",
      "name": "关闭",
      "font_class": "guanbi11",
      "unicode": "e624",
      "unicode_decimal": 58916
    },
    {
      "icon_id": "11641878",
      "name": "加号",
      "font_class": "jiahao20",
      "unicode": "e626",
      "unicode_decimal": 58918
    },
    {
      "icon_id": "12394978",
      "name": "关闭",
      "font_class": "guanbi12",
      "unicode": "e6aa",
      "unicode_decimal": 59050
    },
    {
      "icon_id": "12706015",
      "name": "关闭",
      "font_class": "guanbi13",
      "unicode": "e627",
      "unicode_decimal": 58919
    },
    {
      "icon_id": "14841195",
      "name": "加号",
      "font_class": "jiahao21",
      "unicode": "e628",
      "unicode_decimal": 58920
    },
    {
      "icon_id": "15685022",
      "name": "加号",
      "font_class": "jiahao22",
      "unicode": "e6c0",
      "unicode_decimal": 59072
    },
    {
      "icon_id": "22227203",
      "name": "增加",
      "font_class": "daochu1024-19",
      "unicode": "e629",
      "unicode_decimal": 58921
    },
    {
      "icon_id": "22227215",
      "name": "添加设备",
      "font_class": "daochu1024-29",
      "unicode": "e62a",
      "unicode_decimal": 58922
    },
    {
      "icon_id": "905750",
      "name": "向下箭头",
      "font_class": "xiangxiajiantou6",
      "unicode": "e66b",
      "unicode_decimal": 58987
    },
    {
      "icon_id": "6634557",
      "name": "向下箭头",
      "font_class": "xiangxiajiantou7",
      "unicode": "e622",
      "unicode_decimal": 58914
    },
    {
      "icon_id": "7288601",
      "name": "向下箭头",
      "font_class": "xiangxiajiantou8",
      "unicode": "e770",
      "unicode_decimal": 59248
    },
    {
      "icon_id": "11058440",
      "name": "向下箭头",
      "font_class": "xiangxiajiantou10",
      "unicode": "e654",
      "unicode_decimal": 58964
    },
    {
      "icon_id": "18431453",
      "name": "向下箭头",
      "font_class": "downarrow",
      "unicode": "e603",
      "unicode_decimal": 58883
    },
    {
      "icon_id": "24698889",
      "name": "_向下箭头粗小",
      "font_class": "_xiangxiajiantoucuxiao",
      "unicode": "e8b7",
      "unicode_decimal": 59575
    },
    {
      "icon_id": "24700449",
      "name": "_向下箭头粗小",
      "font_class": "_xiangxiajiantoucuxiao1",
      "unicode": "e8b9",
      "unicode_decimal": 59577
    },
    {
      "icon_id": "7816179",
      "name": "向上箭头",
      "font_class": "xiangshangjiantou4",
      "unicode": "e61b",
      "unicode_decimal": 58907
    },
    {
      "icon_id": "2076428",
      "name": "向上箭头粗小",
      "font_class": "xiangshangjiantoucuxiao",
      "unicode": "e8d8",
      "unicode_decimal": 59608
    },
    {
      "icon_id": "3427880",
      "name": "向上",
      "font_class": "icon-",
      "unicode": "e62c",
      "unicode_decimal": 58924
    },
    {
      "icon_id": "6539449",
      "name": "向上箭头",
      "font_class": "xiangshangjiantou1",
      "unicode": "e68a",
      "unicode_decimal": 59018
    },
    {
      "icon_id": "8133588",
      "name": "向下",
      "font_class": "icon-1",
      "unicode": "e638",
      "unicode_decimal": 58936
    },
    {
      "icon_id": "8551144",
      "name": "23向下箭头",
      "font_class": "xiangxiajiantou2",
      "unicode": "e607",
      "unicode_decimal": 58887
    },
    {
      "icon_id": "8551152",
      "name": "22向上箭头",
      "font_class": "xiangshangjiantou2",
      "unicode": "e609",
      "unicode_decimal": 58889
    },
    {
      "icon_id": "9023913",
      "name": "向上箭头",
      "font_class": "xiangshangjiantou3",
      "unicode": "e69f",
      "unicode_decimal": 59039
    },
    {
      "icon_id": "9523654",
      "name": "向下箭头",
      "font_class": "xiangxiajiantou3",
      "unicode": "e62d",
      "unicode_decimal": 58925
    },
    {
      "icon_id": "9743260",
      "name": "向上箭头-面性",
      "font_class": "shixinjiantou-xiangshang",
      "unicode": "e65b",
      "unicode_decimal": 58971
    },
    {
      "icon_id": "11036685",
      "name": "向下箭头@2x",
      "font_class": "xiangxiajiantoux",
      "unicode": "e640",
      "unicode_decimal": 58944
    },
    {
      "icon_id": "12457913",
      "name": "气泡向下箭头",
      "font_class": "bubble_arrow_down",
      "unicode": "e639",
      "unicode_decimal": 58937
    },
    {
      "icon_id": "17810510",
      "name": "icon_向下箭头粗小",
      "font_class": "icon_xiangxiajiantoucuxiao",
      "unicode": "e63a",
      "unicode_decimal": 58938
    },
    {
      "icon_id": "17810513",
      "name": "icon_向上箭头粗小",
      "font_class": "icon_xiangshangjiantoucuxiao",
      "unicode": "e63b",
      "unicode_decimal": 58939
    },
    {
      "icon_id": "20402197",
      "name": "向下箭头",
      "font_class": "xiangxiajiantou4",
      "unicode": "e6f3",
      "unicode_decimal": 59123
    },
    {
      "icon_id": "24218972",
      "name": "下箭头,指向下箭头",
      "font_class": "a-xiajiantouzhixiangxiajiantou",
      "unicode": "e60d",
      "unicode_decimal": 58893
    },
    {
      "icon_id": "625966",
      "name": "31-向下箭头",
      "font_class": "xiangxiajiantou",
      "unicode": "e61f",
      "unicode_decimal": 58911
    },
    {
      "icon_id": "637803",
      "name": "向上箭头",
      "font_class": "xiangshangjiantou",
      "unicode": "e62f",
      "unicode_decimal": 58927
    },
    {
      "icon_id": "637804",
      "name": "向下箭头",
      "font_class": "xiangxiajiantou1",
      "unicode": "e630",
      "unicode_decimal": 58928
    },
    {
      "icon_id": "1164942",
      "name": "向下箭头_实心",
      "font_class": "xiangxiajiantoushixin",
      "unicode": "e62b",
      "unicode_decimal": 58923
    },
    {
      "icon_id": "2076401",
      "name": " 向下箭头粗小",
      "font_class": "xiangxiajiantoucuxiao",
      "unicode": "e8c8",
      "unicode_decimal": 59592
    },
    {
      "icon_id": "314736",
      "name": "奖杯2",
      "font_class": "2",
      "unicode": "e612",
      "unicode_decimal": 58898
    },
    {
      "icon_id": "314737",
      "name": "奖杯3",
      "font_class": "3",
      "unicode": "e614",
      "unicode_decimal": 58900
    },
    {
      "icon_id": "3180818",
      "name": "奖杯1",
      "font_class": "jiangbei",
      "unicode": "e615",
      "unicode_decimal": 58901
    },
    {
      "icon_id": "3214316",
      "name": "奖杯1",
      "font_class": "jiangbei1",
      "unicode": "e669",
      "unicode_decimal": 58985
    },
    {
      "icon_id": "3550180",
      "name": "奖杯  2",
      "font_class": "jiangbei2",
      "unicode": "e64a",
      "unicode_decimal": 58954
    },
    {
      "icon_id": "3556685",
      "name": "奖杯 3",
      "font_class": "jiangbei3",
      "unicode": "e616",
      "unicode_decimal": 58902
    },
    {
      "icon_id": "4078334",
      "name": "奖杯1",
      "font_class": "1",
      "unicode": "e61c",
      "unicode_decimal": 58908
    },
    {
      "icon_id": "4078335",
      "name": "奖杯3",
      "font_class": "31",
      "unicode": "e61d",
      "unicode_decimal": 58909
    },
    {
      "icon_id": "4078336",
      "name": "奖杯2",
      "font_class": "21",
      "unicode": "e61e",
      "unicode_decimal": 58910
    },
    {
      "icon_id": "6156071",
      "name": "奖杯1",
      "font_class": "jiangbei4",
      "unicode": "e68e",
      "unicode_decimal": 59022
    },
    {
      "icon_id": "6156072",
      "name": "奖杯3",
      "font_class": "jiangbei5",
      "unicode": "e68f",
      "unicode_decimal": 59023
    },
    {
      "icon_id": "6156087",
      "name": "奖杯3",
      "font_class": "jiangbei6",
      "unicode": "e692",
      "unicode_decimal": 59026
    },
    {
      "icon_id": "6156089",
      "name": "奖杯2",
      "font_class": "jiangbei7",
      "unicode": "e693",
      "unicode_decimal": 59027
    },
    {
      "icon_id": "6471699",
      "name": "奖杯-3",
      "font_class": "jiangbei-",
      "unicode": "e777",
      "unicode_decimal": 59255
    },
    {
      "icon_id": "6471700",
      "name": "奖杯-2",
      "font_class": "jiangbei-1",
      "unicode": "e778",
      "unicode_decimal": 59256
    },
    {
      "icon_id": "6796937",
      "name": "奖杯2",
      "font_class": "jiangbei8",
      "unicode": "e88f",
      "unicode_decimal": 59535
    },
    {
      "icon_id": "6796938",
      "name": "奖杯3",
      "font_class": "jiangbei9",
      "unicode": "e890",
      "unicode_decimal": 59536
    },
    {
      "icon_id": "11622192",
      "name": "奖杯 (1)",
      "font_class": "jiangbei10",
      "unicode": "e604",
      "unicode_decimal": 58884
    },
    {
      "icon_id": "14123386",
      "name": "奖杯3",
      "font_class": "jiangbei31",
      "unicode": "e80c",
      "unicode_decimal": 59404
    },
    {
      "icon_id": "14137266",
      "name": "奖杯3",
      "font_class": "jiangbei32",
      "unicode": "e84c",
      "unicode_decimal": 59468
    },
    {
      "icon_id": "16420981",
      "name": "奖杯1",
      "font_class": "jiangbei11",
      "unicode": "e659",
      "unicode_decimal": 58969
    },
    {
      "icon_id": "16420987",
      "name": "奖杯3",
      "font_class": "jiangbei33",
      "unicode": "e65a",
      "unicode_decimal": 58970
    },
    {
      "icon_id": "23918393",
      "name": "奖杯2",
      "font_class": "jiangbei21",
      "unicode": "e697",
      "unicode_decimal": 59031
    },
    {
      "icon_id": "23918396",
      "name": "奖杯1",
      "font_class": "jiangbei12",
      "unicode": "e698",
      "unicode_decimal": 59032
    },
    {
      "icon_id": "23918400",
      "name": "奖杯3",
      "font_class": "jiangbei34",
      "unicode": "e699",
      "unicode_decimal": 59033
    },
    {
      "icon_id": "24874804",
      "name": "奖杯3",
      "font_class": "jiangbei35",
      "unicode": "e6be",
      "unicode_decimal": 59070
    },
    {
      "icon_id": "24874806",
      "name": "奖杯2",
      "font_class": "jiangbei22",
      "unicode": "e6bf",
      "unicode_decimal": 59071
    },
    {
      "icon_id": "4317257",
      "name": "区块-竖条2",
      "font_class": "qukuai-shutiao",
      "unicode": "e625",
      "unicode_decimal": 58917
    },
    {
      "icon_id": "8465392",
      "name": "标题竖条",
      "font_class": "biaotishutiao",
      "unicode": "e60a",
      "unicode_decimal": 58890
    },
    {
      "icon_id": "8580683",
      "name": "标题竖条",
      "font_class": "biaotishutiao1",
      "unicode": "e600",
      "unicode_decimal": 58880
    },
    {
      "icon_id": "11505649",
      "name": "标题竖条",
      "font_class": "biaotishutiao2",
      "unicode": "e601",
      "unicode_decimal": 58881
    },
    {
      "icon_id": "11505852",
      "name": "竖条 ",
      "font_class": "biaotishutiao3",
      "unicode": "e602",
      "unicode_decimal": 58882
    },
    {
      "icon_id": "17792579",
      "name": "竖条",
      "font_class": "shutiao",
      "unicode": "e694",
      "unicode_decimal": 59028
    },
    {
      "icon_id": "21699483",
      "name": "竖条",
      "font_class": "shutiao1",
      "unicode": "e613",
      "unicode_decimal": 58899
    },
    {
      "icon_id": "12911864",
      "name": "对勾",
      "font_class": "duigou",
      "unicode": "e606",
      "unicode_decimal": 58886
    }
  ]
}
